bali/__init__.py
bali/do_string.py
bali/to_string.py
bali-0.0.1.dist-info/LICENSE
bali-0.0.1.dist-info/METADATA
bali-0.0.1.dist-info/WHEEL
bali-0.0.1.dist-info/top_level.txt
bali-0.0.1.dist-info/RECORD
