Metadata-Version: 2.1
Name: bali
Version: 0.0.1
Summary: lombok for python
Home-page: https://github.com/mtngt/bali
Author: mtngt
Author-email: mtngtio@gmail.com
License: MIT
Keywords: Python 3
Platform: UNKNOWN
